crc16/__init__.py
crc16/_crc16.cpython-310-darwin.so
crc16/crc16pure.py
crc16/test.py
pycrc16-0.1.2.dist-info/COPYING.txt
pycrc16-0.1.2.dist-info/METADATA
pycrc16-0.1.2.dist-info/WHEEL
pycrc16-0.1.2.dist-info/top_level.txt
pycrc16-0.1.2.dist-info/RECORD
